{"2022-04-24 15:21:55":{"user":"Жаргал Доржиев","oldBuyout":"10280","oldGross":"11200","oldRetail":"11400","newBuyout":"10280","newGross":"11200","newRetail":"11400"},"2022-04-24 23:29:43":{"user":"Жаргал Доржиев","oldBuyout":"10 280","oldGross":"11 200","oldRetail":"11 400","newBuyout":"10 280","newGross":"11 200","newRetail":"11 400"},"2022-04-24 23:30:27":{"user":"Жаргал Доржиев","oldBuyout":"10280","oldGross":"11200","oldRetail":"11400","newBuyout":"10280","newGross":"11200","newRetail":"11400"}}